{
  "trade_id": "TRD-0043",
  "timestamp": "2026-05-26T16:19:36+08:00",
  "ticker": "002156",
  "action": "buy",
  "account": "a_share",
  "shares": 1100,
  "price": 75.39,
  "value": 82929.0,
  "currency": "CNY",
  "realized_pnl": null,
  "reason": "封装链轮动: 长电涨停溢出, AMD合作方, COMPUTEX 6/1催化, C级仓位",
  "decision_chain": {
    "trigger": {
      "type": "manual",
      "description": "封装链轮动: 长电涨停溢出, AMD合作方, COMPUTEX 6/1催化, C级仓位",
      "source": "execute_trade"
    },
    "risk_check": {
      "pre_trade_cash_pct": 27.65,
      "post_trade_cash_pct": 19.97,
      "position_size_pct": 7.69,
      "single_position_limit_ok": true,
      "cash_minimum_ok": false
    },
    "final_decision": {
      "approved": true,
      "approver": "auto",
      "notes": "封装链轮动: 长电涨停溢出, AMD合作方, COMPUTEX 6/1催化, C级仓位"
    }
  },
  "pre_trade_state": {
    "account_cash_pct": 27.65,
    "account_total_positions": 7,
    "account_nav": 1079081.5
  },
  "post_trade_state": {
    "account_cash_pct": 19.97,
    "account_total_positions": 8,
    "account_nav": 1079081.5,
    "realized_pnl": null
  }
}
