{
  "trade_id": "TRD-0249",
  "timestamp": "2026-06-25T11:06:09+08:00",
  "ticker": "MU",
  "action": "buy",
  "account": "us",
  "shares": 43,
  "price": 1048.51,
  "value": 45085.93,
  "currency": "USD",
  "realized_pnl": null,
  "reason": "MU财报大beat(收入41.5B/Q4指引50B/HBM4快2倍)thesis大幅强化,加至13%,1048现价非追盘后顶1213,不等回调",
  "decision_chain": {
    "trigger": {
      "type": "manual",
      "description": "MU财报大beat(收入41.5B/Q4指引50B/HBM4快2倍)thesis大幅强化,加至13%,1048现价非追盘后顶1213,不等回调",
      "source": "execute_trade"
    },
    "risk_check": {
      "pre_trade_cash_pct": -57.84,
      "post_trade_cash_pct": -60.79,
      "position_size_pct": 13.03,
      "single_position_limit_ok": true,
      "cash_utilization_ok": true
    },
    "final_decision": {
      "approved": true,
      "approver": "auto",
      "notes": "MU财报大beat(收入41.5B/Q4指引50B/HBM4快2倍)thesis大幅强化,加至13%,1048现价非追盘后顶1213,不等回调"
    }
  },
  "pre_trade_state": {
    "account_cash_pct": -57.84,
    "account_total_positions": 12,
    "account_nav": 1529131.9
  },
  "post_trade_state": {
    "account_cash_pct": -60.79,
    "account_total_positions": 12,
    "account_nav": 1529131.9,
    "realized_pnl": null
  }
}
