{
  "trade_id": "TRD-0201",
  "timestamp": "2026-06-11T12:49:21+08:00",
  "ticker": "AVGX",
  "action": "sell",
  "account": "us",
  "shares": 5347,
  "price": 46.12,
  "value": 246603.64,
  "currency": "USD",
  "realized_pnl": -35183.26,
  "reason": "C类下跌:AVGO earnings miss(6/5)破坏beat-cycle thesis,2x decay持续放血;NEUTRAL regime(VIX 22.2)杠杆1.97x超带去杠杆第一步",
  "decision_chain": {
    "trigger": {
      "type": "manual",
      "description": "C类下跌:AVGO earnings miss(6/5)破坏beat-cycle thesis,2x decay持续放血;NEUTRAL regime(VIX 22.2)杠杆1.97x超带去杠杆第一步",
      "source": "execute_trade"
    },
    "risk_check": {
      "pre_trade_cash_pct": -97.39,
      "post_trade_cash_pct": -76.99,
      "position_size_pct": 0.0,
      "single_position_limit_ok": true,
      "cash_utilization_ok": true
    },
    "final_decision": {
      "approved": true,
      "approver": "auto",
      "notes": "C类下跌:AVGO earnings miss(6/5)破坏beat-cycle thesis,2x decay持续放血;NEUTRAL regime(VIX 22.2)杠杆1.97x超带去杠杆第一步"
    }
  },
  "pre_trade_state": {
    "account_cash_pct": -97.39,
    "account_total_positions": 10,
    "account_nav": 1209156.39
  },
  "post_trade_state": {
    "account_cash_pct": -76.99,
    "account_total_positions": 9,
    "account_nav": 1209156.39,
    "realized_pnl": -35183.26
  }
}
