{
  "trade_id": "TRD-0097",
  "timestamp": "2026-06-01T22:33:33+08:00",
  "ticker": "AMD",
  "action": "sell",
  "account": "us",
  "shares": 370,
  "price": 504.91,
  "value": 186816.7,
  "currency": "USD",
  "realized_pnl": -5043.1,
  "reason": "减仓29.8%→~20%: PEG 0.33(Fwd PE 39.8x/CAGR 122%), F9 T3橙灯(bear -27~32%), 单票集中度过高+1.54x杠杆。真正催化剂7/23 Advancing AI。COMPUTEX无AMD重大催化(今日-2.5%最弱)",
  "decision_chain": {
    "trigger": {
      "type": "manual",
      "description": "减仓29.8%→~20%: PEG 0.33(Fwd PE 39.8x/CAGR 122%), F9 T3橙灯(bear -27~32%), 单票集中度过高+1.54x杠杆。真正催化剂7/23 Advancing AI。COMPUTEX无AMD重大催化(今日-2.5%最弱)",
      "source": "execute_trade"
    },
    "risk_check": {
      "pre_trade_cash_pct": -53.43,
      "post_trade_cash_pct": -42.34,
      "position_size_pct": 18.82,
      "single_position_limit_ok": true,
      "cash_minimum_ok": false
    },
    "final_decision": {
      "approved": true,
      "approver": "auto",
      "notes": "减仓29.8%→~20%: PEG 0.33(Fwd PE 39.8x/CAGR 122%), F9 T3橙灯(bear -27~32%), 单票集中度过高+1.54x杠杆。真正催化剂7/23 Advancing AI。COMPUTEX无AMD重大催化(今日-2.5%最弱)"
    }
  },
  "pre_trade_state": {
    "account_cash_pct": -53.43,
    "account_total_positions": 8,
    "account_nav": 1688944.36
  },
  "post_trade_state": {
    "account_cash_pct": -42.34,
    "account_total_positions": 8,
    "account_nav": 1690454.46,
    "realized_pnl": -5043.1
  }
}
