{
  "id": "TRD-0323",
  "timestamp": "2026-07-16T00:46:50+08:00",
  "date": "2026-07-16",
  "action": "sell",
  "account": "a_share",
  "ticker": "000933",
  "name": "神火股份",
  "shares": 26700,
  "price": 23.49,
  "value": 627183.0,
  "currency": "CNY",
  "realized_pnl": 14151.0,
  "reason": "全面重建:按2026-07-10周五收盘价清仓(这几天未管理,重置到周五白纸,从完整扫描头部打分表重建)",
  "decision_chain": {
    "trigger": {
      "type": "rebuild",
      "description": "全面重建清仓@7-10周五收盘",
      "source": "liquidate_0710"
    },
    "final_decision": {
      "approved": true,
      "approver": "auto"
    }
  }
}